Workbook

Sheet Sales Data
A1: Order ID | B1: Order Date | C1: Region | D1: Product | E1: Category | F1: Sales | G1: Profit | H1: Quantity
A2: ORD-1001 | B2: 45432 | C2: North | D2: Pen Set | E2: Office Supplies | F2: 5667.76 | G2: 1997.85 | H2: 8
A3: ORD-1002 | B3: 45594 | C3: North | D3: Markers | E3: Office Supplies | F3: 2012.64 | G3: 230.78 | H3: 14
A4: ORD-1003 | B4: 45579 | C4: North | D4: Headphones | E4: Electronics | F4: 15135.82 | G4: 5138.46 | H4: 7
A5: ORD-1004 | B5: 45593 | C5: West | D5: Desk | E5: Furniture | F5: 21940.38 | G5: 1807.99 | H5: 9
A6: ORD-1005 | B6: 45434 | C6: East | D6: Monitor | E6: Electronics | F6: 3425.9 | G6: 1241.86 | H6: 5
A7: ORD-1006 | B7: 45341 | C7: West | D7: Laptop | E7: Electronics | F7: 30601.32 | G7: 9283.79 | H7: 12
A8: ORD-1007 | B8: 45485 | C8: North | D8: Monitor | E8: Electronics | F8: 5035.56 | G8: 1948.16 | H8: 3
A9: ORD-1008 | B9: 45652 | C9: South | D9: Stapler | E9: Office Supplies | F9: 555.54 | G9: 91.29 | H9: 3
A10: ORD-1009 | B10: 45343 | C10: South | D10: Chair | E10: Furniture | F10: 11310.26 | G10: 3565.03 | H10: 13
A11: ORD-1010 | B11: 45473 | C11: East | D11: Desk | E11: Furniture | F11: 14189.14 | G11: 4819.68 | H11: 7
A12: ORD-1011 | B12: 45565 | C12: South | D12: Pen Set | E12: Office Supplies | F12: 4256.32 | G12: 938.09 | H12: 8
A13: ORD-1012 | B13: 45642 | C13: South | D13: Markers | E13: Office Supplies | F13: 27900.51 | G13: 10242.83 | H13: 11
... A201: ORD-1200 | B201: 45315 | C201: East | D201: Paper Ream | E201: Office Supplies | F201: 9728.24 | G201: 2935.5 | H201: 8

Sheet KPI Analysis
A1: Order ID | B1: Order Date | C1: Region | D1: Product | E1: Category | F1: Sales | G1: Profit | H1: Quantity | I1: Profit Margin | J1: Sales Category
A2: ='Sales Data'!A2 | B2: ='Sales Data'!B2 | C2: ='Sales Data'!C2 | D2: ='Sales Data'!D2 | E2: ='Sales Data'!E2 | F2: ='Sales Data'!F2 | G2: ='Sales Data'!G2 | H2: ='Sales Data'!H2 | I2: =IFERROR(G2/F2,0) | J2: =IF(F2>5000,"High","Medium")
A3: ='Sales Data'!A3 | B3: ='Sales Data'!B3 | C3: ='Sales Data'!C3 | D3: ='Sales Data'!D3 | E3: ='Sales Data'!E3 | F3: ='Sales Data'!F3 | G3: ='Sales Data'!G3 | H3: ='Sales Data'!H3 | I3: =IFERROR(G3/F3,0) | J3: =IF(F3>5000,"High","Medium")
A4: ='Sales Data'!A4 | B4: ='Sales Data'!B4 | C4: ='Sales Data'!C4 | D4: ='Sales Data'!D4 | E4: ='Sales Data'!E4 | F4: ='Sales Data'!F4 | G4: ='Sales Data'!G4 | H4: ='Sales Data'!H4 | I4: =IFERROR(G4/F4,0) | J4: =IF(F4>5000,"High","Medium")
A5: ='Sales Data'!A5 | B5: ='Sales Data'!B5 | C5: ='Sales Data'!C5 | D5: ='Sales Data'!D5 | E5: ='Sales Data'!E5 | F5: ='Sales Data'!F5 | G5: ='Sales Data'!G5 | H5: ='Sales Data'!H5 | I5: =IFERROR(G5/F5,0) | J5: =IF(F5>5000,"High","Medium")
A6: ='Sales Data'!A6 | B6: ='Sales Data'!B6 | C6: ='Sales Data'!C6 | D6: ='Sales Data'!D6 | E6: ='Sales Data'!E6 | F6: ='Sales Data'!F6 | G6: ='Sales Data'!G6 | H6: ='Sales Data'!H6 | I6: =IFERROR(G6/F6,0) | J6: =IF(F6>5000,"High","Medium")
A7: ='Sales Data'!A7 | B7: ='Sales Data'!B7 | C7: ='Sales Data'!C7 | D7: ='Sales Data'!D7 | E7: ='Sales Data'!E7 | F7: ='Sales Data'!F7 | G7: ='Sales Data'!G7 | H7: ='Sales Data'!H7 | I7: =IFERROR(G7/F7,0) | J7: =IF(F7>5000,"High","Medium")
A8: ='Sales Data'!A8 | B8: ='Sales Data'!B8 | C8: ='Sales Data'!C8 | D8: ='Sales Data'!D8 | E8: ='Sales Data'!E8 | F8: ='Sales Data'!F8 | G8: ='Sales Data'!G8 | H8: ='Sales Data'!H8 | I8: =IFERROR(G8/F8,0) | J8: =IF(F8>5000,"High","Medium")
A9: ='Sales Data'!A9 | B9: ='Sales Data'!B9 | C9: ='Sales Data'!C9 | D9: ='Sales Data'!D9 | E9: ='Sales Data'!E9 | F9: ='Sales Data'!F9 | G9: ='Sales Data'!G9 | H9: ='Sales Data'!H9 | I9: =IFERROR(G9/F9,0) | J9: =IF(F9>5000,"High","Medium")
A10: ='Sales Data'!A10 | B10: ='Sales Data'!B10 | C10: ='Sales Data'!C10 | D10: ='Sales Data'!D10 | E10: ='Sales Data'!E10 | F10: ='Sales Data'!F10 | G10: ='Sales Data'!G10 | H10: ='Sales Data'!H10 | I10: =IFERROR(G10/F10,0) | J10: =IF(F10>5000,"High","Medium")
A11: ='Sales Data'!A11 | B11: ='Sales Data'!B11 | C11: ='Sales Data'!C11 | D11: ='Sales Data'!D11 | E11: ='Sales Data'!E11 | F11: ='Sales Data'!F11 | G11: ='Sales Data'!G11 | H11: ='Sales Data'!H11 | I11: =IFERROR(G11/F11,0) | J11: =IF(F11>5000,"High","Medium")
A12: ='Sales Data'!A12 | B12: ='Sales Data'!B12 | C12: ='Sales Data'!C12 | D12: ='Sales Data'!D12 | E12: ='Sales Data'!E12 | F12: ='Sales Data'!F12 | G12: ='Sales Data'!G12 | H12: ='Sales Data'!H12 | I12: =IFERROR(G12/F12,0) | J12: =IF(F12>5000,"High","Medium")
A13: ='Sales Data'!A13 | B13: ='Sales Data'!B13 | C13: ='Sales Data'!C13 | D13: ='Sales Data'!D13 | E13: ='Sales Data'!E13 | F13: ='Sales Data'!F13 | G13: ='Sales Data'!G13 | H13: ='Sales Data'!H13 | I13: =IFERROR(G13/F13,0) | J13: =IF(F13>5000,"High","Medium")
... A201: ='Sales Data'!A201 | B201: ='Sales Data'!B201 | C201: ='Sales Data'!C201 | D201: ='Sales Data'!D201 | E201: ='Sales Data'!E201 | F201: ='Sales Data'!F201 | G201: ='Sales Data'!G201 | H201: ='Sales Data'!H201 | I201: =IFERROR(G201/F201,0) | J201: =IF(F201>5000,"High","Medium")

Sheet Summary KPI
A1: 📊 Sales Performance – Summary KPI
A3: KPI | B3: Value
A4: Total Sales ($) | B4: =SUM('KPI Analysis'!F2:F201)
A5: Total Profit ($) | B5: =SUM('KPI Analysis'!G2:G201)
A6: Average Profit Margin | B6: =AVERAGE('KPI Analysis'!I2:I201)
A7: Total Quantity Sold | B7: =SUM('KPI Analysis'!H2:H201)
A8: Total Orders | B8: =COUNTA('KPI Analysis'!A2:A201)
A9: High Sales Orders | B9: =COUNTIF('KPI Analysis'!J2:J201,"High")

Sheet DAX Measures (Power BI)
A1: DAX Measures Reference – Copy into Power BI
A2: Measure Name | B2: DAX Formula
A3: Total Sales | B3: Total Sales = SUM(SalesData[Sales])
A4: Total Profit | B4: Total Profit = SUM(SalesData[Profit])
A5: Profit Margin | B5: Profit Margin = DIVIDE([Total Profit], [Total Sales])
A6: Total Quantity | B6: Total Quantity = SUM(SalesData[Quantity])
A7: Total Orders | B7: Total Orders = COUNTROWS(SalesData)
A8: Monthly Sales | B8: Monthly Sales = CALCULATE([Total Sales], VALUES(SalesData[Order Date]))
A9: Avg Order Value | B9: Avg Order Value = DIVIDE([Total Sales], [Total Orders])
A10: YTD Sales | B10: YTD Sales = TOTALYTD([Total Sales], SalesData[Order Date])

Sheet Business Insights
B1: 📋 Business Insights & Recommendations
A3: # | B3: KPI / Observation | C3: Insight & Recommendation
A4: 1 | B4: Revenue vs Profit Imbalance | C4: High sales volumes in Electronics do not always translate to high profit margins. Review pricing strategy and supplier costs for low-margin electronic items.
A5: 2 | B5: Regional Performance Gap | C5: Identify which region contributes the highest total profit but lowest order volume — that region likely has high-value customers worth nurturing with loyalty programs.
A6: 3 | B6: Category Contribution | C6: Office Supplies likely drives the highest number of orders (volume) while Electronics drives the highest revenue. Diversify promotions to balance both.
A7: 4 | B7: Seasonal Sales Peaks | C7: Monthly trend analysis reveals sales peaks in Q4 (Oct–Dec). Align inventory and marketing campaigns ahead of the season to maximize revenue.
A8: 5 | B8: Low Margin Products | C8: Products classified as 'High Sales' but showing profit margins below 15% need pricing review or cost renegotiation to protect profitability.
A9: 6 | B9: Quantity vs Revenue Mismatch | C9: Some products sell in high quantities but contribute minimally to revenue — bundle or upsell strategies could improve average order value for these SKUs.
